{"children":[{"name":"rni","class":"Parti","children":[{"name":"Ministere De L'economie Et Des Finances -remboursements, Dégrèvements Et Restitutions, Fiscaux","class":"Ordonnateur","size":5260000000,"color":"rni","label":null},{"name":"Ministere Charge Des Marocains Residant A L'etranger Et Des Affaires De La Migration","class":"Ordonnateur","size":524278000,"color":"rni","label":null},{"name":"Ministere De L'artisanat, De L'economie Sociale Et Solidaire","class":"Ordonnateur","size":633001000,"color":"rni","label":null},{"name":"Ministere Des Affaires Etrangeres Et De  La Cooperation","class":"Ordonnateur","size":2552500000,"color":"rni","label":null},{"name":"Ministere De L'industrie, Du Commerce, De L'investissement  Et De L'economie Numerique","class":"Ordonnateur","size":2791909000,"color":"rni","label":null},{"name":"Ministere De L'economie Et Des Finances","class":"Ordonnateur","size":2832499000,"color":"rni","label":null},{"name":"Ministere De L'agriculture Et De La  Peche Maritime","class":"Ordonnateur","size":11303820000,"color":"rni","label":null},{"name":"Ministere De L'economie Et Des Finances – Charges Communes","class":"Ordonnateur","size":59050000000,"color":"rni","label":null}]},{"name":"ind","class":"Parti","children":[{"name":"Delegation Interministerielle Aux Droits De L'homme","class":"Ordonnateur","size":32003000,"color":"ind","label":null},{"name":"Secretariat General Du Gouvernement","class":"Ordonnateur","size":75976000,"color":"ind","label":null},{"name":"Ministere Delegue Aupres Du Chef Du  Gouvernement Charge Des Affaires Generales Et De La Gouvernance","class":"Ordonnateur","size":81266000,"color":"ind","label":null},{"name":"Conseil Economique, Social Et Environnemental","class":"Ordonnateur","size":124031000,"color":"ind","label":null},{"name":"Haut Commissariat Aux Anciens Resistants Et Anciens Membres De L'armee De Liberation","class":"Ordonnateur","size":128246000,"color":"ind","label":null},{"name":"Juridictions Financieres","class":"Ordonnateur","size":285633000,"color":"ind","label":null},{"name":"Chambre Des Conseillers","class":"Ordonnateur","size":244908000,"color":"ind","label":null},{"name":"Chambre Des Representants","class":"Ordonnateur","size":435121000,"color":"ind","label":null},{"name":"Haut Commissariat Au Plan","class":"Ordonnateur","size":473349000,"color":"ind","label":null},{"name":"Sa Majeste Le Roi","class":"Ordonnateur","size":543456000,"color":"ind","label":null},{"name":"Haut Commissariat Aux Eaux Et Forets Et A La Lutte Contre La Desertification","class":"Ordonnateur","size":697460000,"color":"ind","label":null},{"name":"Delegation Generale A L'administration Penitentiaire Et A La Reinsertion","class":"Ordonnateur","size":1650227000,"color":"ind","label":null},{"name":"Cour Royale","class":"Ordonnateur","size":2069656000,"color":"ind","label":null},{"name":"Depenses Imprevues Et Dotations Provisionnelles","class":"Ordonnateur","size":3300000000,"color":"ind","label":null},{"name":"Ministere Des Habous Et Des Affaires  Islamiques","class":"Ordonnateur","size":3857951000,"color":"ind","label":null},{"name":"Ministere De L'interieur","class":"Ordonnateur","size":21841325000,"color":"ind","label":null},{"name":"Administration De La Defense Nationale","class":"Ordonnateur","size":32631801000,"color":"ind","label":null},{"name":"Ministere De L'education Nationale Et De  La Formation Professionnelle","class":"Ordonnateur","size":45753366000,"color":"ind","label":null}]},{"name":"pjd","class":"Parti","children":[{"name":"Ministere Charge Des Relations Avec Le  Parlement Et La Societe Civile","class":"Ordonnateur","size":42000000,"color":"pjd","label":null},{"name":"Ministere De La Solidarite,De La Femme, De La Famille Et Du Developpement Social","class":"Ordonnateur","size":689163000,"color":"pjd","label":null},{"name":"Chef Du Gouvernement","class":"Ordonnateur","size":1372805000,"color":"pjd","label":null},{"name":"Ministere De La Communication","class":"Ordonnateur","size":1680175000,"color":"pjd","label":null},{"name":"Ministere De L'energie, Des Mines, De  L'eau Et De L'environnement","class":"Ordonnateur","size":4648555000,"color":"pjd","label":null},{"name":"Ministere De La Justice Et Des Libertes","class":"Ordonnateur","size":4450283000,"color":"pjd","label":null},{"name":"Ministere De L'equipement, Du Transport  Et De La Logistique","class":"Ordonnateur","size":7955424000,"color":"pjd","label":null},{"name":"Ministere De L'enseignement Superieur,  De La Recherche Scientifique Et De La Formation Des Cadres","class":"Ordonnateur","size":9892500000,"color":"pjd","label":null}]},{"name":"mp","class":"Parti","children":[{"name":"Ministere Delegue Aupres Du Chef Du  Gouvernement Charge De La Fonction  Publique Et De La Modernisation De L'administration","class":"Ordonnateur","size":117629000,"color":"mp","label":null},{"name":"Ministere Du Tourisme","class":"Ordonnateur","size":798531000,"color":"mp","label":null},{"name":"Ministere De L'urbanisme Et De L'amenagement Du Territoire National","class":"Ordonnateur","size":909485000,"color":"mp","label":null},{"name":"Ministere De La Jeunesse Et Des Sports","class":"Ordonnateur","size":1951596000,"color":"mp","label":null}]},{"name":"pps","class":"Parti","children":[{"name":"Ministere De L'emploi Et Des Affaires Sociales","class":"Ordonnateur","size":527931000,"color":"pps","label":null},{"name":"Ministere De La Culture","class":"Ordonnateur","size":691207000,"color":"pps","label":null},{"name":"Ministere De L'habitat Et De La Politique De La Ville","class":"Ordonnateur","size":829116000,"color":"pps","label":null},{"name":"Ministere De La Sante","class":"Ordonnateur","size":14280934000,"color":"pps","label":null}]}]}